exml/__init__.py
exml/__main__.py
exml/alphabet.py
exml/exml2cqp.py
exml/rad_util.py
exml/schemas.py
exml/topsort.py
exml/tree.py
exmldoc/__init__.py
exmldoc/__main__.py
exmldoc/alphabet.py
exmldoc/binary.py
exmldoc/exml2conll.py
exmldoc/exml2cqp.py
exmldoc/rad_util.py
exmldoc/topsort.py
exmldoc/tree.py
exmldoc/tests/__init__.py
exmldoc/tests/__main__.py
exmldoc/tests/test_alphabet.py
exmldoc/tests/test_exml.py
exmldoc-1.0.4.dist-info/DESCRIPTION.rst
exmldoc-1.0.4.dist-info/METADATA
exmldoc-1.0.4.dist-info/RECORD
exmldoc-1.0.4.dist-info/WHEEL
exmldoc-1.0.4.dist-info/entry_points.txt
exmldoc-1.0.4.dist-info/metadata.json
exmldoc-1.0.4.dist-info/top_level.txt
