Metadata-Version: 2.0
Name: exmldoc
Version: 1.0.4
Summary: Deals with ExportXMLv2 format for annotated text
Home-page: UNKNOWN
Author: Yannick Versley
Author-email: yversley@gmail.com
License: LGPLv3
Platform: UNKNOWN
Classifier: Development Status :: 5 - Production/Stable
Classifier: Intended Audience :: Developers
Classifier: License :: OSI Approved :: GNU Lesser General Public License v3 (LGPLv3)
Classifier: Programming Language :: Python :: 2
Classifier: Programming Language :: Python :: 2.7
Classifier: Topic :: Text Processing :: Linguistic
Requires-Dist: isounidecode
Requires-Dist: mock (>=2.0.0)
Requires-Dist: msgpack-python
Requires-Dist: setuptools (>=19)
Requires-Dist: simplejson
Requires-Dist: sortedcontainers
